lcoe/__init__.py
lcoe/lcoe.py
lcoe-0.3.2.dist-info/AUTHORS.rst
lcoe-0.3.2.dist-info/LICENSE.txt
lcoe-0.3.2.dist-info/METADATA
lcoe-0.3.2.dist-info/WHEEL
lcoe-0.3.2.dist-info/entry_points.txt
lcoe-0.3.2.dist-info/top_level.txt
lcoe-0.3.2.dist-info/RECORD
