Metadata-Version: 2.1
Name: lcoe
Version: 0.3.2
Summary: Micro-package to calculate the levelised cost of electricity
Home-page: https://github.com/willu47/lcoe
Author: Will Usher
Author-email: wusher@kth.se
License: mit
Project-URL: Source, https://github.com/willu47/lcoe
Platform: any
Classifier: Development Status :: 4 - Beta
Classifier: Programming Language :: Python
License-File: LICENSE.txt
License-File: AUTHORS.rst
Requires-Dist: numpy-financial
Requires-Dist: importlib-metadata ; python_version < "3.8"
Provides-Extra: testing
Requires-Dist: pytest ; extra == 'testing'
Requires-Dist: pytest-cov ; extra == 'testing'
